dynamicimporter.py
dynamic_importer-0.0.1.dist-info/METADATA
dynamic_importer-0.0.1.dist-info/WHEEL
dynamic_importer-0.0.1.dist-info/top_level.txt
dynamic_importer-0.0.1.dist-info/RECORD
